kon_quotes/__init__.py
kon_quotes/kon.py
kon_quotes-1.0.1.dist-info/LICENSE.txt
kon_quotes-1.0.1.dist-info/METADATA
kon_quotes-1.0.1.dist-info/WHEEL
kon_quotes-1.0.1.dist-info/top_level.txt
kon_quotes-1.0.1.dist-info/RECORD
