Metadata-Version: 2.1
Name: kon-quotes
Version: 1.0.1
Summary: K-ON Quotes API, get quotes from the K-ON Anime
Home-page: https://github.com/ZeyaTsu/k-on-quotes
Author: ZeyaTsu
Project-URL: Bug Tracker, https://github.com/ZeyaTsu/k-on-quotes/issues
Classifier: Programming Language :: Python :: 3
Classifier: License :: OSI Approved :: MIT License
Classifier: Operating System :: OS Independent
Requires-Python: >=3.6
License-File: LICENSE.txt
